NOTICE
sbml2dae/__init__.py
sbml2dae/cli.py
sbml2dae/dae_model.py
sbml2dae/matlab.py
sbml2dae-0.1.7.dist-info/entry_points.txt
sbml2dae-0.1.7.dist-info/LICENSE
sbml2dae-0.1.7.dist-info/WHEEL
sbml2dae-0.1.7.dist-info/METADATA
sbml2dae-0.1.7.dist-info/RECORD
