Metadata-Version: 2.1
Name: sbml2dae
Version: 0.1.7
Summary: A customizable SBML to Matlab parser
Home-page: https://github.com/sb2cl/sbml2dae
License: Apache-2.0
Keywords: SBML,dae,simulation,parser,MATLAB
Author: Fernando N. Santos Navarro
Author-email: fersann1@upv.es
Requires-Python: >=3.7,<4.0
Classifier: Development Status :: 4 - Beta
Classifier: Intended Audience :: Science/Research
Classifier: License :: OSI Approved :: Apache Software License
Classifier: Operating System :: OS Independent
Classifier: Programming Language :: Python
Classifier: Programming Language :: Python :: 3
Classifier: Programming Language :: Python :: 3 :: Only
Classifier: Programming Language :: Python :: 3.10
Classifier: Programming Language :: Python :: 3.7
Classifier: Programming Language :: Python :: 3.8
Classifier: Programming Language :: Python :: 3.9
Classifier: Topic :: Scientific/Engineering :: Bio-Informatics
Requires-Dist: click (>=8.0.0,<9.0.0)
Requires-Dist: python-libsbml (==5.19.2)
Project-URL: Repository, https://github.com/sb2cl/sbml2dae
